WebDataMiner/Scrapper.py
WebDataMiner/__init__.py
WebDataMiner-0.2.dist-info/METADATA
WebDataMiner-0.2.dist-info/WHEEL
WebDataMiner-0.2.dist-info/top_level.txt
WebDataMiner-0.2.dist-info/RECORD
