Metadata-Version: 2.1
Name: WebDataMiner
Version: 0.2
Summary: A web scraper that downloads tables, images, and text from a webpage
Home-page: https://gitlab.kaisens.fr/kaisensdata/apps/4inshield/drivers/generic-crawler/-/tree/asaid
Author: Said Mohamed Amine
Author-email: mohamedamine.said@enetcom.u-sfax.tn
Classifier: Development Status :: 3 - Alpha
Classifier: Intended Audience :: Developers
Classifier: License :: OSI Approved :: MIT License
Classifier: Programming Language :: Python :: 3
Classifier: Programming Language :: Python :: 3.6
Classifier: Programming Language :: Python :: 3.7
Classifier: Programming Language :: Python :: 3.8
Classifier: Programming Language :: Python :: 3.9
Requires-Dist: beautifulsoup4
Requires-Dist: pandas
Requires-Dist: lxml
Requires-Dist: requests
Requires-Dist: tqdm
Requires-Dist: selenium
